{
  "fallback": "dimensiondelvers:rift/terminator",

  "elements": [
    {

      "weight": 80,
      "element": {

        "location": "dimensiondelvers:rift/passage/ring_stable",

        "processors": "dimensiondelvers:forest",

        "projection": "rigid",

        "element_type": "minecraft:single_pool_element"
      }
    },
    {

      "weight": 20,
      "element": {

        "location": "dimensiondelvers:rift/passage/ring_unstable",

        "processors": "dimensiondelvers:forest",

        "projection": "rigid",

        "element_type": "minecraft:single_pool_element"
      }
    }
  ]
}